{
  "id": "9e0602880723cf1b9b6955407d01cea6ae4525b2",
  "source_url": "if://regulatory/fiscal-tax-cb/2025-12-03/part-4",
  "source_type": "regulatory_intelligence",
  "retrieved_at": "2025-12-03T20:20:05.560450+00:00",
  "metadata": {
    "research_type": "fiscal_tax_cb",
    "part": 4,
    "total_parts": 6,
    "depth": "comprehensive"
  },
  "content": "- **Deadline:** June 30, 2024 for meeting new capital thresholds\n- **Governance:** Compliance with 2024 Corporate Governance Regulations required\n- **Source:** BoU/UMRA regulatory framework\n\n---\n\n### RWANDA\n\n#### Tax Regime\n- **Corporate Tax Rate:** 28% (effective September 14, 2024 onwards; previously 30% for income up to September 13, 2024)\n  - **Pro-Rata 2024:** 30% (Jan 1 - Sep 13), 28% (Sep 14 - Dec 31)\n  - **Medium-Term Target:** 20% corporate tax rate\n- **Micro-Enterprises (<RWF 12M turnover):** Flat tax amounts based on turnover\n- **Small Businesses (RWF 12M - 20M turnover):** 3% lump sum tax on turnover\n- **Deposit-Taking Microfinance Institutions (Competent Authority Approved):** 0% CIT for 5 years from approval\n- **Financial Services (Registered Investors):** 15% preferential CIT rate for global business, private equity funds, fund management, wealth management, mutual funds, collective investment schemes, captive insurance, venture capital, asset-backed securities\n- **VAT Rate:** 18% standard rate\n- **VAT Exemptions:** Clean water, health goods/services, educational materials/services, transport (except land), books/newspapers/journals, financial and insurance services, land/building leases for residential purposes\n- **VAT Registration Threshold:** RWF 20 million annual taxable turnover OR RWF 5 million in a calendar quarter\n- **Withholding Tax:** 15% on dividends, financial interest, royalties, repatriated profits, etc.; 5% on imported goods for commercial use; 3% on public tender winners (15% if not registered with tax admin or no prior tax declaration)\n- **Tax Clearance Certificate Benefit:** Businesses with certificate exempted from all WHT deductions\n- **Gaming WHT:** 15% on difference between winnings and stake\n- **Source:** [Rwanda Tax Guide 2024](https://www.hlbrwanda.com/wp-content/uploads/2024/12/HLB-Rwanda-2024-Tax-Guide-2_240925_210103.pdf), [Rwanda Corporate Tax PWC](https://taxsummaries.pwc.com/rwanda/corporate/taxes-on-corporate-income)\n\n#### Central Bank Circulars & Regulations\n- **Regulatory Authority:** National Bank of Rwanda (BNR)\n- **Historical Licensing Framework (2008):**\n  - **Commercial Banks:** RWF 5 billion minimum paid-up capital\n  - **Microfinance Banks:** RWF 1.5 billion minimum paid-up capital\n  - **Development Banks:** RWF 3 billion minimum paid-up capital\n  - **Source:** [BNR Licensing Changes 2018](https://en.igihe.com/news/bnr-introduces-changes-in-licensing-requirements)\n\n- **2018 Regulatory Changes:**\n  - **Commercial Banks:** RWF 20 billion paid-up capital (NEW)\n  - **Development Banks:** RWF 50 billion paid-up capital (NEW)\n  - **Cooperative Banks (NEW category):** RWF 10 billion paid-up capital\n  - **Mortgage Banks (NEW category):** RWF 10 billion paid-up capital\n  - **Transition Period:** 5 years to build capital (RWF 15 billion by year 3, full RWF 20 billion by year 5)\n  - **Source:** [UNCTAD Rwanda Central Bank Requirements](https://investmentpolicy.unctad.org/investment-policy-monitor/measures/3344/rwanda-central-bank-introduces-new-requirements-for-licensing-financial-institutions)\n\n- **Current Status (2023-2025):**\n  - **Banking Sector Composition (Dec 2023):** 9 commercial banks, 3 microfinance banks, 1 development bank, 1 cooperative bank\n  - **Anticipated Changes:** Three microfinance banks expected to transition from bank category to MFI category to comply with new capital requirements\n  - **Foreign Presence Requirement:** Approximately $20 million minimum share capital to establish banking presence in Rwanda\n  - **Capital Adequacy (2025):** Banks 20.5% (above 15% minimum), MFIs 32.3% (above 15% minimum)\n  - **Source:** [Rwanda Monetary Policy March 2024](https://www.bnr.rw/documents/MPFSS_March_2024_Final_Booklet.pdf), [Rwanda Monetary Policy March 2025](https://www.bnr.rw/documents/MPFSS_Report_March_2025.pdf)\n\n#### Licensing Requirements\n- **Application:** Submit to National Bank of Rwanda with business model demonstrating market gap\n- **Capital:** Approximately $20 million minimum share capital for banks\n- **Business Model:** Must demonstrate gap in market\n- **Microfinance Institutions:** Capital requirements distinct from microfinance banks (specific amounts require direct BNR consultation)\n- **Source:** [BNR Licensing Requirements](https://www.bnr.rw/financial-stability/microfinance-institutions/licensing-and-approval-requirements/)\n\n---\n\n## TIER 4: EGYPT, MOROCCO (NORTH AFRICA)\n\n### EGYPT\n\n#### Tax Regime\n- **Corporate Tax Rate:** 22.5% flat rate on net taxable income (applies to all businesses including foreign-owned companies, LLCs, branches)\n- **VAT Rate:** 14% standard rate\n- **Reduced VAT (5%):** Machinery and equipment for manufacturing and service provision (payment suspended on imported or locally purchased items)\n- **VAT Registration Threshold:** EGP 500,000 annual turnover\n- **Zero-Rated VAT:** Exports of goods/services, goods/services from free zones\n- **Withholding Tax:** 20% standard rate\n  - **Interest on Loans (Private Sector):** Exempt if >3 years; 20% WHT if <3 years\n  - **Royalty Payments:** 20% WHT\n  - **Treaty Reductions:** 65+ treaties; most reduce interest WHT to 15%, royalties to 5-15% (from 20%)\n- **Stamp Tax:** Two types - nominal (e.g., EGP 1 per contract paper) and proportional (0.05%-0.3% based on transaction value)\n- **Bank Loan Stamp Tax:** 0.4% annual proportional stamp tax (shared by bank and client)\n- **Source:** [Egypt Tax System GSL](https://gsl.org/en/taxes/egypt/), [Egypt Corporate Tax PWC](https://taxsummaries.pwc.com/egypt/corporate/taxes-on-corporate-income)\n\n#### Central Bank Circulars & Regulations\n- **Regulatory Framework:** Dual regulation by Financial Regulatory Authority (FRA) and Central Bank of Egypt (CBE)\n- **Primary Microfinance Regulator:** FRA under Microfinance Law No. 141 of 2014 (+ amendments)\n\n- **Capital Requirements:**\n  - **Non-Banking Fintech Entities (Microfinance under FRA):**\n    - **Start-ups (Temporary 2-year license):** EGP 15 million for some activities (less stringent)\n    - **Established Market Players:** EGP 75 million for some activities\n  - **CBE Payment Service Providers (Category-Based):**\n    - **Category A PSPs:** EGP 30 million minimum capital\n    - **Category B PSPs:** EGP 10 million minimum capital\n    - **Account Information/Payment Initiation Service Providers:** EGP 20 million minimum capital\n  - **Digital Banks (for context):** EGP 4 billion issued and fully paid-up capital (or USD 120 million for foreign bank digital branches)\n  - **Grace Period (PSPs):** 12 months for existing payment institutions to comply with new rules\n  - **Source:** [Egypt Fintech 2024](https://practiceguides.chambers.com/practice-guides/fintech-2024/egypt), [CBE Payment System Rules 2025](https://www.cbe.org.eg/en/news-publications/news/2025/06/19/08/20/psos-and-psps-licensing-rules)\n\n- **CBE Requirements for Microlending:**\n  - **Electronic Payment License:** Required from CBE for fintech entities in micro-lending\n  - **Credit Inquiry Contract:** Must have contract with CBE-licensed credit inquiry company\n  - **Federation Membership:** Must join Egyptian Federation for Financing Medium, Small and Micro Enterprises\n  - **Source:** [Microlending Egypt Compliance Guide](https://eg.andersen.com/microlending-in-egypt/)\n\n- **Data Requirements (2024):**\n  - **NDPC Guidance (Feb 2024):** Entities processing data for >200 individuals in 6 months OR operating in finance, healthcare, education sectors qualify as Data Controllers and Processors of Major Importance (DCPMIs)\n  - **African Union Convention:** Nigeria signed AU Convention on Cybersecurity and Personal Data Protection (Jan 2024) - includes data rights, security, enforcement provisions\n  - **Source:** [CBE Digital Banks Framework](https://www.tamimi.com/news/the-central-bank-of-egypt-introduces-the-regulatory-framework-and-licensing-requirements-for-digital-banks/)\n\n#### Licensing Requirements\n- **FRA License:** Required for microfinance services; demonstrate capital adequacy, consumer protection, operational guidelines compliance\n- **CBE License:** Electronic payment solutions license required for micro-lending fintech entities\n- **Application:** Submit to FRA with compliance documentation\n- **Capital:** EGP 15 million (start-ups) to EGP 75 million (established players) for fintech microfinance\n- **Source:** FRA and CBE regulatory framework\n\n---\n\n### MOROCCO\n\n#### Tax Regime\n- **Corporate Tax Rate:** 35% for companies with net tax income ≥ MAD 100 million\n  - **Reduced Rate:** 20% if net profit below MAD 100 million for 3 consecutive years\n  - **Phased Implementation:** Target rates 20%/35% fully applicable January 2026 (progressive 2023-2026)\n- **VAT Standard Rate:** 20%\n- **VAT Reduced Rate:** 10% for banking/credit services, leasing, gas, water, electricity\n- **VAT for Insurance Agents/Brokers:** 14% (being phased out in 2024 reforms)\n- **VAT Transition (2024-2026):** Gradual transition to 0%, 10%, 20% rates only\n- **Withholding Tax:**\n  - **Dividends (Resident Company):** NOT subject to WHT\n  - **Dividends (Resident Individual):** 12.5%\n  - **Dividends (Non-Resident):** 10%\n  - **Interest (Resident Company):** 20%\n  - **Interest (Resident Individual):** 30%\n  - **Interest (Non-Resident Loan):** 10% (unless reduced by treaty)\n  - **Interest (Non-Resident Loan ≥10 years):** EXEMPT\n  - **Royalties (Resident):** EXEMPT\n  - **Royalties (Non-Resident):** 10%\n- **Branch Tax:** 15% on net income transferred to foreign entities\n- **VAT Withholding (2024 New Measure - Effective July 1, 2024):**\n  - **Rate:** 75% of VAT withheld by State/public entities on equipment suppliers failing to present recent tax compliance certificate\n  - **No Certificate:** 100% VAT withholding\n  - **Source:** [Morocco Tax 2024 Finance Law](https://auditcloud.ma/2023/12/14/tax-provisions-of-the-2024-finance-law-in-morocco/), [Morocco Corporate Tax PWC](https://taxsummaries.pwc.com/morocco/corporate/taxes-on-corporate-income)\n\n#### Central Bank Circulars & Regulations\n- **Regulatory Authority:** Bank Al-Maghrib\n- **Legal Framework:** Law No. 103-12 on credit institutions and similar bodies (Royal Decree No. 1-14-193, December 24, 2014)\n- **Scope:** Banks, finance companies, offshore banks, microcredit associations, payment institutions, Deposit and Management Fund, Central Guarantee Fund\n\n- **Bank Al-Maghrib Licensing Authority:**\n  - **Extended Prerogatives:** Licensing of microcredit associations and offshore banks (in addition to credit institutions)\n  - **Regulation Power:** Elaboration of regulations governing activity\n  - **Problem-Addressing:** License withdrawal authority\n  - **Source:** [Bank Al-Maghrib Licensing](https://www.bkam.ma/en/Banking-supervision/Micro-prudential-supervision/Licensing)\n\n- **Licensing Application Requirements:**\n  - **Institution Documents:** Bye-laws, supervisory authority opinion (parent company), shareholders' agreement\n  - **Capital Provider Information:** Details on capital providers, managers, directors\n  - **Additional Documentation:** Bank Al-Maghrib may require further information via Circular No. 5/W/2023\n  - **Licensing Models:** Bank Al-Maghrib may create licensing models for each credit institution category and/or operation type\n  - **Source:** [Morocco Banking Regulation](https://www.mondaq.com/finance-and-banking/1085608/banking-regulation-comparative-guide)\n\n- **Microfinance Regulation:**\n  - **Circular No. 5/W/2023:** Relates to classification of receivables held by microfinance institutions licensed as credit establishments and coverage by provisions\n  - **Prudential Rules:** MFIs bound by Bank Al-Maghrib prudential rules applicable to credit institutions\n  - **Verification:** Bank Al-Maghrib verifies adequacy of administrative/accounting organization and internal control systems\n  - **Financial Quality:** Ensures quality of MFI financial situation"
}